{"status":"done","publicPath":"http://localhost:8080/dist/","chunks":{"main":[{"name":"build.js","publicPath":"http://localhost:8080/dist/build.js","path":"E:\\Django-with-Vue-CLI\\frontend\\dist\\build.js"},{"name":"0.e313b4386bf41fe74f67.hot-update.js","publicPath":"http://localhost:8080/dist/0.e313b4386bf41fe74f67.hot-update.js","path":"E:\\Django-with-Vue-CLI\\frontend\\dist\\0.e313b4386bf41fe74f67.hot-update.js"}]},"error":"ModuleError","message":"(Emitted value instead of an instance of Error) \n  Error compiling template:\n  \n  <div class=\"container\">\n      <div class=\"col-md-2\">\n          <div class=\"col-lg-4 col-md-4 col-sm-4 col-xs-12\">\n              <div class=\"box-part text-center shadow p-3 mb-5 bg-white rounded\">\n                   Basic Details\n                  \n              </div>\n          </div>\n      </div>\n  <div class=\"col-md-10\">\n              hi\n          </div>\n      </div>\n      <div class=\"row\">\n          <div class=\"col-md-2\">\n              Work\n          </div>\n          <div class=\"col-md-10\">\n              hi\n          </div>\n      </div>\n      <div class=\"row\">\n          <div class=\"col-md-2\">\n              Education\n          </div>\n          <div class=\"col-md-10\">\n              hi\n          </div>\n      </div>\n  </div>\n  \n  - Component template should contain exactly one root element. If you are using v-if on multiple elements, use v-else-if to chain them instead.\n"}